st_textnav_component/__init__.py
st_textnav_component/frontend/build/asset-manifest.json
st_textnav_component/frontend/build/bootstrap.min.css
st_textnav_component/frontend/build/index.html
st_textnav_component/frontend/build/precache-manifest.8b423b587c604604c1d98234c4c05999.js
st_textnav_component/frontend/build/service-worker.js
st_textnav_component/frontend/build/static/js/2.ec6e7411.chunk.js
st_textnav_component/frontend/build/static/js/2.ec6e7411.chunk.js.LICENSE.txt
st_textnav_component/frontend/build/static/js/2.ec6e7411.chunk.js.map
st_textnav_component/frontend/build/static/js/main.c0c5ac3d.chunk.js
st_textnav_component/frontend/build/static/js/main.c0c5ac3d.chunk.js.map
st_textnav_component/frontend/build/static/js/runtime-main.5875292e.js
st_textnav_component/frontend/build/static/js/runtime-main.5875292e.js.map
st_textnav_component-0.0.1.dist-info/LICENSE
st_textnav_component-0.0.1.dist-info/METADATA
st_textnav_component-0.0.1.dist-info/WHEEL
st_textnav_component-0.0.1.dist-info/top_level.txt
st_textnav_component-0.0.1.dist-info/RECORD
